odoo/addons/sale_order_import_edifact/README.rst
odoo/addons/sale_order_import_edifact/__init__.py
odoo/addons/sale_order_import_edifact/__manifest__.py
odoo/addons/sale_order_import_edifact/demo/demo_data.xml
odoo/addons/sale_order_import_edifact/i18n/es.po
odoo/addons/sale_order_import_edifact/i18n/fr.po
odoo/addons/sale_order_import_edifact/i18n/it.po
odoo/addons/sale_order_import_edifact/i18n/sale_order_import_edifact.pot
odoo/addons/sale_order_import_edifact/models/__init__.py
odoo/addons/sale_order_import_edifact/models/business_document_import.py
odoo/addons/sale_order_import_edifact/readme/CONFIGURE.rst
odoo/addons/sale_order_import_edifact/readme/CONTRIBUTORS.rst
odoo/addons/sale_order_import_edifact/readme/CREDITS.rst
odoo/addons/sale_order_import_edifact/readme/DESCRIPTION.rst
odoo/addons/sale_order_import_edifact/readme/HISTORY.rst
odoo/addons/sale_order_import_edifact/readme/ROADMAP.rst
odoo/addons/sale_order_import_edifact/static/description/icon.png
odoo/addons/sale_order_import_edifact/static/description/icon.svg
odoo/addons/sale_order_import_edifact/static/description/index.html
odoo/addons/sale_order_import_edifact/tests/__init__.py
odoo/addons/sale_order_import_edifact/tests/common.py
odoo/addons/sale_order_import_edifact/tests/test_edifact_order_import.py
odoo/addons/sale_order_import_edifact/wizard/__init__.py
odoo/addons/sale_order_import_edifact/wizard/sale_order_import.py
odoo/addons/sale_order_import_edifact/wizard/sale_order_import_view.xml
odoo_addon_sale_order_import_edifact-16.0.1.1.0.4.dist-info/METADATA
odoo_addon_sale_order_import_edifact-16.0.1.1.0.4.dist-info/WHEEL
odoo_addon_sale_order_import_edifact-16.0.1.1.0.4.dist-info/top_level.txt
odoo_addon_sale_order_import_edifact-16.0.1.1.0.4.dist-info/RECORD
